cmdline/__init__.py
cmdline/cmdline.py
cmdline_mini-1.0.2.dist-info/LICENSE
cmdline_mini-1.0.2.dist-info/WHEEL
cmdline_mini-1.0.2.dist-info/METADATA
cmdline_mini-1.0.2.dist-info/RECORD
